{
  "project_info": {
    "project_number": "575243185292",
    "project_id": "simplesample-66800",
    "storage_bucket": "simplesample-66800.appspot.com"
  },
  "client": [
    {
      "client_info": {
        "mobilesdk_app_id": "1:575243185292:android:1da1736885aa828e3c1fa9",
        "android_client_info": {
          "package_name": "com.example.simple_sample"
        }
      },
      "oauth_client": [
        {
          "client_id": "575243185292-ejpcemudgiscecdcdhpeaibvktdnrf9l.apps.googleusercontent.com",
          "client_type": 3
        }
      ],
      "api_key": [
        {
          "current_key": "AIzaSyCDdmPn9LWpL9zEcXjF8Id_iVxFmHoveMc"
        }
      ],
      "services": {
        "appinvite_service": {
          "other_platform_oauth_client": [
            {
              "client_id": "575243185292-ejpcemudgiscecdcdhpeaibvktdnrf9l.apps.googleusercontent.com",
              "client_type": 3
            }
          ]
        }
      }
    }
  ],
  "configuration_version": "1"
}